MANIFEST.in
README.md
pyproject.toml
setup.py
GQuery/__init__.py
GQuery/config_slience.py
GQuery/main.py
GQuery/model.py
GQuery/structure.py
GQuery/torchTrans.py
GQuery.egg-info/PKG-INFO
GQuery.egg-info/SOURCES.txt
GQuery.egg-info/dependency_links.txt
GQuery.egg-info/not-zip-safe
GQuery.egg-info/requires.txt
GQuery.egg-info/top_level.txt
GQuery/rfmini/Complex.h
GQuery/rfmini/__init__.py
GQuery/rfmini/cmat2.h
GQuery/rfmini/defaults.h
GQuery/rfmini/fork.cpp
GQuery/rfmini/greens.cpp
GQuery/rfmini/model.cpp
GQuery/rfmini/model.h
GQuery/rfmini/pd.cpp
GQuery/rfmini/rf.h
GQuery/rfmini/rfmini.c
GQuery/rfmini/rfmini.pyx
GQuery/rfmini/setup.py
GQuery/rfmini/synrf.cpp
GQuery/rfmini/synrf.h
GQuery/rfmini/wave.h
GQuery/rfmini/wrap.cpp