Metadata-Version: 2.1
Name: GQuery
Version: 0.1.0
Requires-Dist: keras==3.2.1
Requires-Dist: dispCal
Requires-Dist: torch
Requires-Dist: scipy
Requires-Dist: numpy
Requires-Dist: matplotlib
Requires-Dist: netCDF4
